Metadata-Version: 2.1
Name: djangorestframework-verbose-errors
Version: 0.0.6
Summary: A simple package for DRF errors formatting
Home-page: https://github.com/koenigsley/djangorestframework-verbose-errors
Author: Mikhail Yeremeyev
Author-email: koenigsley@gmail.com
License: MIT
Platform: UNKNOWN
Requires-Python: >=3.6
License-File: LICENSE
